fba/__init__.py
fba/__main__.py
fba/count.py
fba/demultiplex.py
fba/filter.py
fba/kallisto.py
fba/levenshtein.py
fba/map.py
fba/parsers.py
fba/qc.py
fba/regex.py
fba/utils.py
fba-0.0.13.dist-info/LICENSE
fba-0.0.13.dist-info/METADATA
fba-0.0.13.dist-info/WHEEL
fba-0.0.13.dist-info/entry_points.txt
fba-0.0.13.dist-info/top_level.txt
fba-0.0.13.dist-info/RECORD
