Metadata-Version: 2.1
Name: fba
Version: 0.0.13
Summary: Tools for single-cell feature barcoding analysis
Author-email: Jialei Duan <t4mi27b3v@relay.firefox.com>
License: MIT License
Project-URL: Homepage, https://github.com/jlduan/fba
Keywords: cell-hashing,cell-partitioning,cellplex,cite-seq,crispr,eccite-seq,feature-barcodes,multi-seq,phage-atac,single-cell,targeted-transcripts
Classifier: Development Status :: 5 - Production/Stable
Classifier: Intended Audience :: Science/Research
Classifier: License :: OSI Approved :: MIT License
Classifier: Operating System :: MacOS :: MacOS X
Classifier: Operating System :: POSIX :: Linux
Classifier: Operating System :: Unix
Classifier: Programming Language :: Python :: 3
Classifier: Topic :: Scientific/Engineering :: Bio-Informatics
Requires-Python: >=3.6
License-File: LICENSE
Requires-Dist: dnaio (>=0.10.0)
Requires-Dist: hdbscan
Requires-Dist: matplotlib (>=3.3)
Requires-Dist: numpy
Requires-Dist: pandas
Requires-Dist: polyleven (>=0.5)
Requires-Dist: pyclustering
Requires-Dist: pysam (>=0.14.0)
Requires-Dist: regex
Requires-Dist: scikit-learn
Requires-Dist: scipy
Requires-Dist: seaborn
Requires-Dist: statsmodels
Requires-Dist: umap-learn
Requires-Dist: umi-tools (>=1.0.0)
